minimax_package/__init__.py
minimax_package/minimax.py
minimax-0.0.1.dist-info/LICENSE
minimax-0.0.1.dist-info/METADATA
minimax-0.0.1.dist-info/WHEEL
minimax-0.0.1.dist-info/top_level.txt
minimax-0.0.1.dist-info/RECORD
