Metadata-Version: 2.1
Name: minimax
Version: 0.0.1
Summary: A configurable minimax package
Home-page: https://github.com/bergurtareqtamimi/minimax_package
Author: Bergur Tareq
Author-email: bergurtamimi@gmail.com
License: UNKNOWN
Platform: UNKNOWN
Classifier: Programming Language :: Python :: 3
Classifier: License :: OSI Approved :: MIT License
Classifier: Operating System :: OS Independent
Requires-Python: >=3.10
License-File: LICENSE
